instagram/bind.py
instagram/client.py
instagram/helper.py
instagram/json_import.py
instagram/models.py
instagram/oauth2.py
instagram/subscriptions.py
instagram/__init__.py
instagram-1.3.4.dist-info/DESCRIPTION.rst
instagram-1.3.4.dist-info/METADATA
instagram-1.3.4.dist-info/metadata.json
instagram-1.3.4.dist-info/RECORD
instagram-1.3.4.dist-info/top_level.txt
instagram-1.3.4.dist-info/WHEEL
instagram-1.3.4.dist-info/zip-safe
