Metadata-Version: 1.0
Name: instagram
Version: 1.3.4
Summary: Instagram API client
Home-page: http://github.com/wkoot/python-instagram
Author: instagram, wkoot
Author-email: pypi@rondarchief.nl
License: MIT
Keywords: instagram
Platform: UNKNOWN
